minimum_jerk/__init__.py
minimum_jerk/get_terms.py
minimum_jerk/minjerk.py
minimum_jerk/minjerk_analytic.py
minimum_jerk/minjerk_penalty.py
minimum_jerk/mytypes.py
minimum_jerk/utils.py
minimum_jerk-0.1.0.dist-info/LICENSE
minimum_jerk-0.1.0.dist-info/METADATA
minimum_jerk-0.1.0.dist-info/WHEEL
minimum_jerk-0.1.0.dist-info/top_level.txt
minimum_jerk-0.1.0.dist-info/RECORD
