Metadata-Version: 2.1
Name: minimum-jerk
Version: 0.1.0
Summary: Path planning using minimum jerk algorithm.
Home-page: https://github.com/HaoMAFRLu/MinimumJerk
Author: Hao Ma
Author-email: hao.ma@tuebingen.mpg.de
License: UNKNOWN
Platform: UNKNOWN
Classifier: Development Status :: 2 - Pre-Alpha
Classifier: Intended Audience :: Science/Research
Classifier: License :: OSI Approved :: MIT License
Classifier: Programming Language :: Python :: 3.8
Requires-Python: >=3.8
